printStatus/__init__.py
printStatus/printStatus.py
printStatus-1.0.6.dist-info/LICENSE
printStatus-1.0.6.dist-info/METADATA
printStatus-1.0.6.dist-info/WHEEL
printStatus-1.0.6.dist-info/top_level.txt
printStatus-1.0.6.dist-info/RECORD
