Metadata-Version: 2.1
Name: printStatus
Version: 1.0.6
Summary: Display a progress bar and the status of a job in the console
Home-page: https://abittner.gitlab.io/home/
Author: Adrian Bittner
Author-email: adrian.bittner@eso.org
License: Other/Proprietary License
Platform: UNKNOWN
Classifier: Development Status :: 5 - Production/Stable
Classifier: Programming Language :: Python :: 3
Requires-Python: >=3
